crm1/__init__.py
crm1/autorepotools.py
crm1/helpers/__init__.py
crm1/helpers/versions.py
crm1/spec/__init__.py
crm1/spec/v1/__init__.py
crm1/spec/v1/common_modext.py
crm1/spec/v1/dependency.py
crm1/spec/v1/mod.py
crm1/spec/v1/repository.py
crm1/spec/v2/__init__.py
crm1/spec/v2/common_modext.py
crm1/spec/v2/dependency.py
crm1/spec/v2/mod.py
crm1/spec/v2/repository.py
crm1/types/__init__.py
crm1/types/dependency.py
crm1/types/mod.py
crm1/types/repository.py
crm1/types/repository_pool.py
crm1/utils.py
crm1-0.1.1.dist-info/LICENSE
crm1-0.1.1.dist-info/METADATA
crm1-0.1.1.dist-info/WHEEL
crm1-0.1.1.dist-info/RECORD
