Metadata-Version: 2.1
Name: crm1
Version: 0.1.1
Summary: A CRM-1 repository exploration package
Home-page: https://github.com/J0J0HA/py-crm1
License: MIT
Keywords: crm1,repository,exploration,python
Author: JoJoJux
Author-email: johannes@jojojux.de
Requires-Python: >=3.10,<4.0
Classifier: License :: OSI Approved :: MIT License
Classifier: Programming Language :: Python :: 3
Classifier: Programming Language :: Python :: 3.10
Classifier: Programming Language :: Python :: 3.11
Classifier: Programming Language :: Python :: 3.12
Requires-Dist: dataclasses-hjson (>=0.0.3,<0.0.4)
Requires-Dist: hjson (>=3.1.0,<4.0.0)
Requires-Dist: requests (>=2.31.0,<3.0.0)
Project-URL: Repository, https://github.com/J0J0HA/py-crm1
